licence.txt
main.py
setup.cfg
setup.py
BS/QS.py
BS/__init__.py
BS/binary_search.py
BS/__pycache__/__init__.cpython-38.pyc
IS/Interpolation_search.py
IS/QS.py
IS/__init__.py
QS/QS.py
QS/__init__.py
QS/__pycache__/QS.cpython-38.pyc
QS/__pycache__/__init__.cpython-38.pyc
QS/__pycache__/h.cpython-38.pyc
pyArrayTool.egg-info/PKG-INFO
pyArrayTool.egg-info/SOURCES.txt
pyArrayTool.egg-info/dependency_links.txt
pyArrayTool.egg-info/not-zip-safe
pyArrayTool.egg-info/top_level.txt