Metadata-Version: 1.0
Name: pyArrayTool
Version: 0.10
Summary: binary search, quicksort and interpolation search
Home-page: UNKNOWN
Author: UNKNOWN
Author-email: UNKNOWN
License: UNKNOWN
Platform: UNKNOWN
